ez_setup.py
setup.cfg
setup.py
NetCube.egg-info/PKG-INFO
NetCube.egg-info/SOURCES.txt
NetCube.egg-info/dependency_links.txt
NetCube.egg-info/entry_points.txt
NetCube.egg-info/requires.txt
NetCube.egg-info/top_level.txt
cube/COPYING
cube/LICENSE
cube/__init__.py
cube/config.py
cube/controllers.py
cube/cube.py
cube/default.cfg
cube/display.py
cube/graphics.py
cube/network.py
cube/preferences.py
cube/scenegraph.py
cube/screen.png
cube/vector.py
