Metadata-Version: 1.0
Name: NetCube
Version: 0.3.0
Summary: Python implementation of the Spinning Cube of Potential Doom.
Home-page: http://echospiral.com/trac/cube
Author: Jeffrey Kyllo
Author-email: jkyllo-cube@echospiral.com
License: GPLv2
Keywords: network,dump,cube,trace,OpenGL,pcap,capture
Platform: UNKNOWN
Classifier: Development Status :: 4 - Beta
Classifier: Environment :: Console
Classifier: Environment :: MacOS X
Classifier: Environment :: Win32 (MS Windows)
Classifier: Environment :: X11 Applications
Classifier: Intended Audience :: Information Technology
Classifier: Intended Audience :: System Administrators
Classifier: License :: DFSG approved
Classifier: License :: OSI Approved :: GNU General Public License (GPL)
Classifier: Operating System :: OS Independent
Classifier: Programming Language :: Python
Classifier: Natural Language :: English
Classifier: Topic :: System :: Networking :: Monitoring
Classifier: Topic :: Utilities
Classifier: Topic :: Security
